[{"id": 1, "itemid": 59001, "name": "gold"}, {"id": 2, "itemid": 59002, "name": "oil"}, {"id": 3, "itemid": 59003, "name": "exploit"}, {"id": 4, "itemid": 59004, "name": "gem"}, {"id": 6, "itemid": 59006, "name": "dormMoney"}, {"id": 8, "itemid": 59008, "name": "guildCoin"}, {"id": 9, "itemid": 59009, "name": "design_prt"}, {"id": 11, "itemid": 59015, "name": "gamecoin"}, {"id": 12, "itemid": 59016, "name": "gameticket"}, {"id": 14, "itemid": 59005, "name": "freeGem"}, {"id": 15, "itemid": 59017, "name": "soundStoryCard"}, {"id": 16, "itemid": 59001, "name": "gold_mail"}, {"id": 17, "itemid": 59002, "name": "oil_mail"}, {"id": 103, "itemid": 59104, "name": "ema"}, {"id": 104, "itemid": 59105, "name": "star"}, {"id": 105, "itemid": 59106, "name": "grace"}, {"id": 106, "itemid": 59107, "name": "ema1"}, {"id": 108, "itemid": 59109, "name": "omamori"}, {"id": 110, "itemid": 59111, "name": "yisegefuke_pt"}, {"id": 111, "itemid": 59112, "name": "faxipt"}, {"id": 112, "itemid": 59113, "name": "jiujiu"}, {"id": 113, "itemid": 59115, "name": "nvpu_pt"}, {"id": 114, "itemid": 59116, "name": "zhandouzhixing"}, {"id": 115, "itemid": 59117, "name": "chuansonghaogan"}, {"id": 116, "itemid": 59118, "name": "chuansong"}, {"id": 117, "itemid": 59119, "name": "longxiang"}, {"id": 118, "itemid": 59120, "name": "tiancheng"}, {"id": 119, "itemid": 59121, "name": "British_pt"}, {"id": 120, "itemid": 59123, "name": "naerweikehaogan"}, {"id": 121, "itemid": 59124, "name": "omamori1"}, {"id": 122, "itemid": 59125, "name": "battery1"}, {"id": 123, "itemid": 59126, "name": "kizuna_pt"}, {"id": 124, "itemid": 59127, "name": "union_pt"}, {"id": 125, "itemid": 59128, "name": "skinTicket"}, {"id": 126, "itemid": 59129, "name": "bisimai_pt"}, {"id": 127, "itemid": 59130, "name": "xiaoshengdiyagehaogan"}, {"id": 130, "itemid": 59133, "name": "faxi_pt"}, {"id": 131, "itemid": 59134, "name": "newmeixi_pt"}, {"id": 132, "itemid": 59135, "name": "qixihaibao_pt"}, {"id": 133, "itemid": 59137, "name": "yidali_pt"}, {"id": 134, "itemid": 59138, "name": "xunliandianshu"}, {"id": 135, "itemid": 59139, "name": "union2_pt"}, {"id": 136, "itemid": 59140, "name": "skinTicket2"}, {"id": 137, "itemid": 59143, "name": "ouxiang_pt"}, {"id": 138, "itemid": 59144, "name": "hololive_pt"}, {"id": 139, "itemid": 59145, "name": "dashenling_pt"}, {"id": 140, "itemid": 59146, "name": "xunliandianshu_r"}, {"id": 141, "itemid": 59147, "name": "xinrixi_pt"}, {"id": 142, "itemid": 59148, "name": "xunliandianshu_m"}, {"id": 143, "itemid": 59149, "name": "maoxi_pt"}, {"id": 144, "itemid": 59150, "name": "skinTicket3"}, {"id": 145, "itemid": 59151, "name": "longxiang2"}, {"id": 146, "itemid": 59152, "name": "sofmap_pt"}, {"id": 147, "itemid": 59153, "name": "battery2"}, {"id": 148, "itemid": 59154, "name": "xunliandianshu_v3"}, {"id": 149, "itemid": 59155, "name": "meixiv3_pt"}, {"id": 150, "itemid": 59156, "name": "skinTicket4"}, {"id": 151, "itemid": 59157, "name": "tiancheng2"}, {"id": 152, "itemid": 59158, "name": "xiaoshengwang_pt"}, {"id": 153, "itemid": 59159, "name": "skinTicket5"}, {"id": 154, "itemid": 59160, "name": "xunliandianshu_fv2"}, {"id": 157, "itemid": 59163, "name": "bishengke_pt"}, {"id": 159, "itemid": 59165, "name": "faxiv2_pt"}, {"id": 160, "itemid": 59168, "name": "skinTicket6"}, {"id": 161, "itemid": 59169, "name": "naerweike2_pt"}, {"id": 162, "itemid": 59170, "name": "xunliandianshu_yv2"}, {"id": 163, "itemid": 59171, "name": "yingxiv2_pt"}, {"id": 164, "itemid": 59172, "name": "skinTicket7"}, {"id": 165, "itemid": 59173, "name": "meifu2_pt"}, {"id": 166, "itemid": 59174, "name": "bisimai_pt2"}, {"id": 167, "itemid": 59175, "name": "skinTicket8"}, {"id": 168, "itemid": 59176, "name": "union4_pt"}, {"id": 169, "itemid": 59180, "name": "shinanoframept"}, {"id": 170, "itemid": 59181, "name": "skinTicket9"}, {"id": 171, "itemid": 59182, "name": "shinano_pt"}, {"id": 172, "itemid": 59183, "name": "pulinsidun_pt"}, {"id": 173, "itemid": 59186, "name": "skinTicket10"}, {"id": 175, "itemid": 59185, "name": "ouxiang2_pt"}, {"id": 176, "itemid": 59188, "name": "naerweikehaogan2"}, {"id": 177, "itemid": 59189, "name": "DOApt"}, {"id": 178, "itemid": 59190, "name": "skinTicket11"}, {"id": 179, "itemid": 59191, "name": "dexiv3framept"}, {"id": 180, "itemid": 59192, "name": "dexiv3_pt"}, {"id": 181, "itemid": 59193, "name": "skinTicket12"}, {"id": 182, "itemid": 59195, "name": "yidalifukeframept"}, {"id": 183, "itemid": 59196, "name": "yidali_pt2"}, {"id": 184, "itemid": 59197, "name": "skinTicket13"}, {"id": 185, "itemid": 59198, "name": "skinTicket14"}, {"id": 186, "itemid": 59199, "name": "chunjie_pt"}, {"id": 187, "itemid": 59200, "name": "maoxiv2framept"}, {"id": 188, "itemid": 59201, "name": "maoxiv2_pt"}, {"id": 189, "itemid": 59202, "name": "skinTicket15"}, {"id": 190, "itemid": 59203, "name": "wwf2"}, {"id": 191, "itemid": 59204, "name": "wwf2_ning"}, {"id": 192, "itemid": 59205, "name": "wwf2_ping"}, {"id": 193, "itemid": 59206, "name": "yidaliv2_frame"}, {"id": 194, "itemid": 59207, "name": "newmeixire_pt"}, {"id": 195, "itemid": 59208, "name": "skinTicket16"}, {"id": 196, "itemid": 59209, "name": "yidaliV2_pt"}, {"id": 197, "itemid": 59210, "name": "skinTicket17"}, {"id": 198, "itemid": 59211, "name": "xiaotiancheng_pt"}, {"id": 199, "itemid": 59212, "name": "newmeixiv4framept"}, {"id": 200, "itemid": 59213, "name": "xiongxiaobai_pt"}, {"id": 201, "itemid": 59214, "name": "xinzexi_pt"}, {"id": 202, "itemid": 59215, "name": "skinTicket18"}, {"id": 203, "itemid": 59216, "name": "xiaoqiye_pt"}, {"id": 204, "itemid": 59217, "name": "union5_pt"}, {"id": 205, "itemid": 59219, "name": "duihuanquan_pt"}, {"id": 206, "itemid": 59221, "name": "xunliandianshu_r2"}, {"id": 207, "itemid": 59222, "name": "TWkaifuPT1"}, {"id": 208, "itemid": 59223, "name": "xinrixi_pt2"}, {"id": 209, "itemid": 59224, "name": "skinTicket19"}, {"id": 211, "itemid": 59229, "name": "meixiv3_pt2"}, {"id": 212, "itemid": 59235, "name": "rixiv2_pt"}, {"id": 215, "itemid": 59230, "name": "idolMasterPT"}, {"id": 216, "itemid": 59231, "name": "skinTicket20"}, {"id": 217, "itemid": 59232, "name": "xunliandianshu_v3_2"}, {"id": 218, "itemid": 59233, "name": "skinTicket21"}, {"id": 219, "itemid": 59234, "name": "daofeng_pt"}, {"id": 220, "itemid": 59238, "name": "union6_pt"}, {"id": 221, "itemid": 59240, "name": "skinTicket22"}, {"id": 222, "itemid": 59243, "name": "faxiv2_frame_pt"}, {"id": 223, "itemid": 59246, "name": "faxiv2_pt2"}, {"id": 224, "itemid": 59248, "name": "skinTicket23"}, {"id": 225, "itemid": 59249, "name": "skinTicket24"}, {"id": 226, "itemid": 59250, "name": "fuxu_pt"}, {"id": 227, "itemid": 59251, "name": "gulite_pt"}, {"id": 228, "itemid": 59252, "name": "skinTicket25"}, {"id": 229, "itemid": 59255, "name": "xiaoshengdiyagehaogan_2"}, {"id": 230, "itemid": 59256, "name": "dexiv4framept"}, {"id": 231, "itemid": 59257, "name": "skinTicket26"}, {"id": 232, "itemid": 59258, "name": "dexiur_pt"}, {"id": 234, "itemid": 59263, "name": "chunjie_pt2"}, {"id": 235, "itemid": 59264, "name": "skinTicket27"}, {"id": 236, "itemid": 59271, "name": "maoxi_pt2"}, {"id": 237, "itemid": 59272, "name": "maoxifukeframept"}, {"id": 238, "itemid": 59273, "name": "skinTicket28"}, {"id": 239, "itemid": 59275, "name": "maoxiv3_frame_pt"}, {"id": 240, "itemid": 59276, "name": "maoxiv3_pt"}, {"id": 241, "itemid": 59277, "name": "skinTicket29"}, {"id": 242, "itemid": 59278, "name": "naerweike2re_pt"}, {"id": 243, "itemid": 59279, "name": "yidalisp_pt"}, {"id": 244, "itemid": 59282, "name": "skinTicket30"}, {"id": 245, "itemid": 59283, "name": "yingxiv2re_pt"}, {"id": 246, "itemid": 59285, "name": "skinTicket31"}, {"id": 247, "itemid": 59286, "name": "xiaoshengwang_pt2"}, {"id": 248, "itemid": 59287, "name": "yingxiv2re_frame_pt1"}, {"id": 250, "itemid": 59305, "name": "gonghaijiandui_frame_pt"}, {"id": 251, "itemid": 59307, "name": "gonghaijiandui_pt"}, {"id": 252, "itemid": 59308, "name": "xiaoougen_pt"}, {"id": 253, "itemid": 59309, "name": "xiaoougen_youhao_pt"}, {"id": 254, "itemid": 59310, "name": "skinTicket32"}, {"id": 255, "itemid": 59311, "name": "yingxiur_frame_pt"}, {"id": 260, "itemid": 59316, "name": "yingxiv3_pt"}, {"id": 261, "itemid": 59317, "name": "skinTicket33"}, {"id": 262, "itemid": 59318, "name": "xiaochaijun_pt"}, {"id": 263, "itemid": 59319, "name": "xiaochaijun_youhao_pt"}, {"id": 264, "itemid": 59320, "name": "union7_pt"}, {"id": 265, "itemid": 59321, "name": "pulinsidun_pt2"}, {"id": 266, "itemid": 59322, "name": "commission_pt"}, {"id": 267, "itemid": 59325, "name": "skinTicket34"}, {"id": 268, "itemid": 59326, "name": "shinano_frame_pt2"}, {"id": 269, "itemid": 59328, "name": "shinano_pt2"}, {"id": 270, "itemid": 59329, "name": "skinTicket35"}, {"id": 271, "itemid": 59331, "name": "yidaliv3_pt"}, {"id": 272, "itemid": 59333, "name": "skinTicket36"}, {"id": 273, "itemid": 59334, "name": "meifu2_pt_re"}, {"id": 274, "itemid": 59336, "name": "bulvxieer_pt"}, {"id": 275, "itemid": 59337, "name": "skinTicket37"}, {"id": 276, "itemid": 59338, "name": "kfc_pt"}, {"id": 277, "itemid": 59345, "name": "rixiv3_pt"}, {"id": 278, "itemid": 59346, "name": "skinTicket38"}, {"id": 279, "itemid": 59348, "name": "union8_pt"}, {"id": 280, "itemid": 59350, "name": "xiaosipei_pt"}, {"id": 281, "itemid": 59351, "name": "yongzhe_pt"}, {"id": 282, "itemid": 59354, "name": "skinTicket39"}, {"id": 283, "itemid": 59357, "name": "dexiv3_pt2"}, {"id": 284, "itemid": 59359, "name": "skinTicket40"}, {"id": 286, "itemid": 59363, "name": "ryza_task_pt"}, {"id": 287, "itemid": 59364, "name": "ryza_pt"}, {"id": 288, "itemid": 59365, "name": "skinTicket41"}, {"id": 290, "itemid": 59371, "name": "wenquanjuan_pt"}, {"id": 291, "itemid": 59372, "name": "xinnianzhufu_pt"}, {"id": 292, "itemid": 59373, "name": "meixierxing_pt"}, {"id": 293, "itemid": 59374, "name": "skinTicket42"}, {"id": 295, "itemid": 59377, "name": "maoxiv2_pt2"}, {"id": 296, "itemid": 59378, "name": "skinTicket43"}, {"id": 297, "itemid": 59389, "name": "skinTicket44"}, {"id": 300, "itemid": 59390, "name": "chunjie_pt3"}, {"id": 301, "itemid": 59391, "name": "feicaizhixing_pt"}, {"id": 302, "itemid": 59395, "name": "yingxiv4_pt"}, {"id": 303, "itemid": 59396, "name": "skinTicket45"}, {"id": 304, "itemid": 59398, "name": "yidaliV2"}, {"id": 305, "itemid": 59399, "name": "skinTicket46"}, {"id": 306, "itemid": 59401, "name": "xiaotiancheng_pt2"}, {"id": 307, "itemid": 59402, "name": "commission_pt2"}, {"id": 308, "itemid": 59405, "name": "jidifengbao_pt"}, {"id": 309, "itemid": 59406, "name": "skinTicket47"}, {"id": 310, "itemid": 59408, "name": "newserver_pt_230427"}, {"id": 311, "itemid": 59409, "name": "xiaoqiye_pt2"}, {"id": 312, "itemid": 59410, "name": "fuxu1_pt"}, {"id": 313, "itemid": 59411, "name": "xiaokewei_pt"}, {"id": 315, "itemid": 59420, "name": "DOApt_2"}, {"id": 316, "itemid": 59421, "name": "skinTicket48"}, {"id": 317, "itemid": 59548, "name": "xiaochaijun_pt2"}, {"id": 318, "itemid": 59549, "name": "xiaochaijun_youhao_pt2"}, {"id": 319, "itemid": 59572, "name": "xiaoxinnong_pt"}, {"id": 320, "itemid": 59576, "name": "xiaosipei_pt2"}, {"id": 321, "itemid": 59585, "name": "xiaofeitelie_pt"}, {"id": 350, "itemid": 59450, "name": "liuzhounianhaidao_pt"}, {"id": 351, "itemid": 59452, "name": "bsmz_pt"}, {"id": 352, "itemid": 59453, "name": "skinTicket49"}, {"id": 353, "itemid": 59454, "name": "union9_pt"}, {"id": 354, "itemid": 59457, "name": "island_invitation_pt"}, {"id": 355, "itemid": 59458, "name": "xiaodafeng_youhao_pt"}, {"id": 356, "itemid": 59459, "name": "xinzexi_pt1"}, {"id": 357, "itemid": 59461, "name": "skinTicket50"}, {"id": 358, "itemid": 59465, "name": "skinTicket51"}, {"id": 359, "itemid": 59466, "name": "gulite_pt_2"}, {"id": 360, "itemid": 59469, "name": "skinTicket52"}, {"id": 361, "itemid": 59470, "name": "masaiqu_pt"}, {"id": 365, "itemid": 59481, "name": "klms_pt"}, {"id": 366, "itemid": 59480, "name": "skinTicket55"}, {"id": 367, "itemid": 59482, "name": "partyinvitation_pt"}, {"id": 368, "itemid": 59485, "name": "yunxian_pt"}, {"id": 369, "itemid": 59487, "name": "zuma_pt"}, {"id": 370, "itemid": 59491, "name": "skinTicket56"}, {"id": 371, "itemid": 59492, "name": "union10_pt"}, {"id": 375, "itemid": 59495, "name": "skinTicket58"}, {"id": 376, "itemid": 59497, "name": "haidao_pt"}, {"id": 377, "itemid": 59498, "name": "skinTicket59"}, {"id": 378, "itemid": 59500, "name": "rixiv2_pt1"}, {"id": 379, "itemid": 59501, "name": "commission_pt3"}, {"id": 380, "itemid": 59506, "name": "shanluan_pt"}, {"id": 381, "itemid": 59508, "name": "shanluan_mission_pt"}, {"id": 382, "itemid": 59509, "name": "skinTicket60"}, {"id": 383, "itemid": 59512, "name": "newserver_pt_231123"}, {"id": 384, "itemid": 59515, "name": "xinghai_pt1"}, {"id": 385, "itemid": 59516, "name": "xinghai_pt2"}, {"id": 386, "itemid": 59517, "name": "skinTicket61"}, {"id": 387, "itemid": 59518, "name": "skinTicket62"}, {"id": 388, "itemid": 59519, "name": "dexiur_pt2"}, {"id": 389, "itemid": 59520, "name": "dexiv4framept2"}, {"id": 390, "itemid": 59522, "name": "skinTicket63"}, {"id": 391, "itemid": 59391, "name": "feicaizhixing2024_pt"}, {"id": 392, "itemid": 59527, "name": "skinTicket64"}, {"id": 393, "itemid": 59528, "name": "chunjie_pt4"}, {"id": 394, "itemid": 59529, "name": "skinTicket65"}, {"id": 395, "itemid": 59531, "name": "skinTicket66"}, {"id": 396, "itemid": 59532, "name": "tongmeng_pt"}, {"id": 397, "itemid": 59533, "name": "yidalisp_pt2"}, {"id": 398, "itemid": 59534, "name": "skinTicket67"}, {"id": 399, "itemid": 59536, "name": "yongzhe_pt2"}, {"id": 400, "itemid": 59539, "name": "skinTicket68"}, {"id": 401, "itemid": 59542, "name": "yishijie_jinbi"}, {"id": 402, "itemid": 59543, "name": "yishijie_exp"}, {"id": 403, "itemid": 59544, "name": "maoxiv3_pt2"}, {"id": 404, "itemid": 59545, "name": "maoxiv3_frame_pt2"}, {"id": 405, "itemid": 59547, "name": "skinTicket69"}, {"id": 406, "itemid": 59570, "name": "skinTicket70"}, {"id": 407, "itemid": 59571, "name": "ouxiang3_pt"}, {"id": 409, "itemid": 59578, "name": "skinTicket71"}, {"id": 410, "itemid": 59579, "name": "huiguang_pt1"}, {"id": 411, "itemid": 59580, "name": "huiguang_pt2"}, {"id": 413, "itemid": 59586, "name": "skinTicket72"}, {"id": 950, "itemid": 59111, "name": "yisegefuke_pt1"}, {"id": 951, "itemid": 99950, "name": "unionkr_pt"}, {"id": 952, "itemid": 99951, "name": "skinTicketkr"}, {"id": 953, "itemid": 99956, "name": "battery3"}, {"id": 954, "itemid": 99957, "name": "unionkr_pt_2021"}, {"id": 955, "itemid": 99957, "name": "unionkr_pt_2021_2"}, {"id": 1001, "itemid": 59136, "name": "vote2019_pt"}, {"id": 2001, "itemid": 59122, "name": "contribution_worldboss"}, {"id": 2002, "itemid": 59141, "name": "contribution_worldboss926"}, {"id": 2003, "itemid": 59142, "name": "worldboss926_ticket"}, {"id": 2004, "itemid": 59967, "name": "nvpu2_pt"}, {"id": 2005, "itemid": 59968, "name": "nvpu_ticket"}, {"id": 2006, "itemid": 60057, "name": "contribution_worldboss624"}, {"id": 2007, "itemid": 60058, "name": "worldboss624_ticket"}, {"id": 2008, "itemid": 59225, "name": "contribution_worldboss708"}, {"id": 2009, "itemid": 59226, "name": "worldboss708_ticket"}, {"id": 2010, "itemid": 59265, "name": "contribution_worldboss127"}, {"id": 2011, "itemid": 59266, "name": "worldboss127_ticket"}, {"id": 2012, "itemid": 59323, "name": "contribution_worldboss630"}, {"id": 2013, "itemid": 59324, "name": "worldboss630_ticket"}, {"id": 2014, "itemid": 59352, "name": "contribution_worldboss6301"}, {"id": 2015, "itemid": 59353, "name": "worldboss630_ticket1"}, {"id": 2016, "itemid": 59380, "name": "contribution_worldboss118"}, {"id": 2017, "itemid": 59381, "name": "worldboss118_ticket"}, {"id": 2018, "itemid": 59463, "name": "contribution_worldboss230629"}, {"id": 2019, "itemid": 59464, "name": "worldboss230629_ticket"}, {"id": 2020, "itemid": 59523, "name": "contribution_worldboss240130"}, {"id": 2021, "itemid": 59524, "name": "worldboss230130_ticket"}, {"id": 3000, "itemid": 69000, "name": "guild_boss_damage"}, {"id": 3001, "itemid": 21901, "name": "synchronize_ark"}, {"id": 3002, "itemid": 110002, "name": "dashijiechongzhi"}, {"id": 3003, "itemid": 21902, "name": "synchronize_huangjiafangzhou"}, {"id": 3004, "itemid": 21903, "name": "synchronize_hailunna"}, {"id": 3005, "itemid": 21904, "name": "synchronize_canglong"}, {"id": 3006, "itemid": 21905, "name": "synchronize_genaisennao"}, {"id": 3007, "itemid": 21906, "name": "synchronize_shaenhuosite"}, {"id": 3008, "itemid": 21907, "name": "synchronize_fanji"}, {"id": 3009, "itemid": 21908, "name": "synchronize_fanji1"}, {"id": 3010, "itemid": 21909, "name": "synchronize_yalisangna"}, {"id": 3011, "itemid": 21910, "name": "synchronize_yilishabai"}, {"id": 3012, "itemid": 21911, "name": "synchronize_aerjiliya"}, {"id": 3013, "itemid": 21912, "name": "synchronize_shentong"}, {"id": 3014, "itemid": 21913, "name": "synchronize_jiluofu"}, {"id": 3015, "itemid": 21914, "name": "synchronize_luodeni"}, {"id": 3106, "itemid": 59107, "name": "twhongran_pt"}, {"id": 4001, "itemid": 59241, "name": "battlepass_1"}, {"id": 4002, "itemid": 59253, "name": "battlepass_2"}, {"id": 4003, "itemid": 59269, "name": "battlepass_3"}, {"id": 4004, "itemid": 59280, "name": "battlepass_4"}, {"id": 4005, "itemid": 59290, "name": "battlepass_5"}, {"id": 4006, "itemid": 59293, "name": "battlepass_6"}, {"id": 4007, "itemid": 59295, "name": "battlepass_7"}, {"id": 4008, "itemid": 59296, "name": "battlepass_8"}, {"id": 4009, "itemid": 59298, "name": "Battlepass_9"}, {"id": 4010, "itemid": 59403, "name": "Battlepass_10"}, {"id": 4011, "itemid": 59455, "name": "Battlepass_11"}, {"id": 4012, "itemid": 59467, "name": "Battlepass_12"}, {"id": 4013, "itemid": 59493, "name": "Battlepass_13"}, {"id": 4014, "itemid": 59510, "name": "Battlepass_14"}, {"id": 4015, "itemid": 59525, "name": "Battlepass_15"}, {"id": 4016, "itemid": 59540, "name": "Battlepass_16"}, {"id": 4017, "itemid": 59583, "name": "Battlepass_17"}, {"id": 40275, "itemid": 59143, "name": "Twouxiang_pt"}]