[{"collection_id":3,"desc":"A piece of the aircraft you arrived on the island with.","icon":"IslandProps/morensuipian","id":1001,"name":"Aircraft Debris","object_list":[10010058],"show":1,"task":0,"time_taked":10,"tip":"Might be located at Morningdew Farm."},{"collection_id":3,"desc":"A piece of the aircraft you arrived on the island with.","icon":"IslandProps/morensuipian","id":1002,"name":"Aircraft Debris","object_list":[10010059],"show":1,"task":0,"time_taked":10,"tip":"Might be located at Morningdew Farm."},{"collection_id":3,"desc":"A piece of the aircraft you arrived on the island with.","icon":"IslandProps/morensuipian","id":1003,"name":"Aircraft Debris","object_list":[10010060],"show":1,"task":0,"time_taked":10,"tip":"Might be located at Morningdew Farm."},{"collection_id":3,"desc":"A piece of the aircraft you arrived on the island with.","icon":"IslandProps/morensuipian","id":1004,"name":"Aircraft Debris","object_list":[10010061],"show":1,"task":0,"time_taked":10,"tip":"Might be located at Morningdew Farm."},{"collection_id":3,"desc":"A piece of the aircraft you arrived on the island with.","icon":"IslandProps/morensuipian","id":1005,"name":"Aircraft Debris","object_list":[10010062],"show":1,"task":0,"time_taked":10,"tip":"Might be located at Morningdew Farm."},{"collection_id":2,"desc":"A piece of the aircraft you arrived on the island with.","icon":"IslandProps/morensuipian","id":1006,"name":"Aircraft Debris","object_list":[10040046],"show":1,"task":0,"time_taked":10,"tip":"Might be located at the Windswept Plains."},{"collection_id":2,"desc":"A piece of the aircraft you arrived on the island with.","icon":"IslandProps/morensuipian","id":1007,"name":"Aircraft Debris","object_list":[10040047],"show":1,"task":0,"time_taked":10,"tip":"Might be located at the Windswept Plains."},{"collection_id":2,"desc":"A piece of the aircraft you arrived on the island with.","icon":"IslandProps/morensuipian","id":1008,"name":"Aircraft Debris","object_list":[10040048],"show":1,"task":0,"time_taked":10,"tip":"Might be located at the Windswept Plains."},{"collection_id":2,"desc":"A piece of the aircraft you arrived on the island with.","icon":"IslandProps/morensuipian","id":1009,"name":"Aircraft Debris","object_list":[10040049],"show":1,"task":0,"time_taked":10,"tip":"Might be located at the Windswept Plains."},{"collection_id":1,"desc":"A piece of the aircraft you arrived on the island with.","icon":"IslandProps/morensuipian","id":1010,"name":"Aircraft Debris","object_list":[10020008],"show":1,"task":0,"time_taked":10,"tip":"Might be located at the harbor."},{"collection_id":1,"desc":"A piece of the aircraft you arrived on the island with.","icon":"IslandProps/morensuipian","id":1011,"name":"Aircraft Debris","object_list":[10020014],"show":1,"task":0,"time_taked":10,"tip":"Might be located at the harbor."},{"collection_id":1,"desc":"A piece of the aircraft you arrived on the island with.","icon":"IslandProps/morensuipian","id":1012,"name":"Aircraft Debris","object_list":[10020015],"show":1,"task":0,"time_taked":10,"tip":"Might be located at the harbor."}]
